art_modern_utils/__init__.py
art_modern_utils/art_profile_fastqc.py
art_modern_utils/art_sam_validate.py
art_modern_utils-0.1.0.dist-info/licenses/License.md
art_modern_utils-0.1.0.dist-info/METADATA
art_modern_utils-0.1.0.dist-info/WHEEL
art_modern_utils-0.1.0.dist-info/entry_points.txt
art_modern_utils-0.1.0.dist-info/top_level.txt
art_modern_utils-0.1.0.dist-info/RECORD
