Metadata-Version: 2.4
Name: art_modern_utils
Version: 0.1.0
Summary: Python Ultilities for art_modern
Author-email: YU Zhejian <yuzj25@seas.upenn.edu>
Project-URL: Source, https://github.com/YU-Zhejian/art_modern_utils
Classifier: Development Status :: 4 - Beta
Classifier: Environment :: Console
Classifier: Intended Audience :: Developers
Classifier: Intended Audience :: Healthcare Industry
Classifier: Intended Audience :: Science/Research
Classifier: License :: OSI Approved :: GNU General Public License v3 (GPLv3)
Classifier: Natural Language :: English
Classifier: Operating System :: MacOS :: MacOS X
Classifier: Operating System :: POSIX
Classifier: Programming Language :: Python :: 3 :: Only
Classifier: Programming Language :: Python :: 3.9
Classifier: Programming Language :: Python :: 3.10
Classifier: Programming Language :: Python :: 3.11
Classifier: Programming Language :: Python :: 3.12
Classifier: Programming Language :: Python :: 3.13
Classifier: Programming Language :: Python :: Implementation :: CPython
Classifier: Programming Language :: R
Classifier: Topic :: Scientific/Engineering :: Bio-Informatics
Classifier: Topic :: Utilities
Requires-Python: >=3.9
License-File: License.md
Requires-Dist: pysam
Requires-Dist: tqdm
Requires-Dist: numpy
Requires-Dist: matplotlib
Dynamic: license-file
